hoadleyYaPu/__init__.py
hoadleyYaPu/hoadleyYaPu.py
hoadleyYaPu-0.2.dist-info/METADATA
hoadleyYaPu-0.2.dist-info/WHEEL
hoadleyYaPu-0.2.dist-info/top_level.txt
hoadleyYaPu-0.2.dist-info/RECORD
