Metadata-Version: 2.1
Name: hoadleyYaPu
Version: 0.2
Summary: A package for Black-Scholes option pricing and implied volatility calculation(European Options only)
Home-page: https://github.com/iam7pY/hoadleyYaPu
Author: Yash Purohit
Author-email: yashpurohit1234@gmail.com
Classifier: Programming Language :: Python :: 3
Classifier: License :: OSI Approved :: MIT License
Classifier: Operating System :: OS Independent
Requires-Python: >=3.6
Requires-Dist: numpy
Requires-Dist: scipy
